grafica/__init__.py
grafica/breadcrumbs.html
grafica/footer.html
grafica/header.html
grafica/layout.html
grafica/localtoc.html
grafica/page.html
grafica/search.html
grafica/theme.toml
grafica/static/css/theme.css
grafica/static/icons/github.svg
grafica/static/icons/instagram.png
grafica/static/icons/twitter.png
grafica/static/icons/youtube.png
grafica/static/js/css.js
grafica-0.2.0.dist-info/licenses/LICENSE
grafica-0.2.0.dist-info/METADATA
grafica-0.2.0.dist-info/WHEEL
grafica-0.2.0.dist-info/entry_points.txt
grafica-0.2.0.dist-info/top_level.txt
grafica-0.2.0.dist-info/RECORD
