Metadata-Version: 2.4
Name: grafica
Version: 0.2.0
Summary: Un tema de Sphinx basado en gob.mx
Author-email: Jacob Sánchez <jacobszpz@protonmail.com>
Project-URL: Repository, https://github.com/sanjacob/grafica
Classifier: Framework :: Sphinx
Classifier: Framework :: Sphinx :: Theme
Classifier: Development Status :: 5 - Production/Stable
Classifier: Environment :: Web Environment
Classifier: Intended Audience :: Developers
Classifier: Programming Language :: Python :: 3
Classifier: Programming Language :: Python :: 3.8
Classifier: Programming Language :: Python :: 3.9
Classifier: Programming Language :: Python :: 3.10
Classifier: Programming Language :: Python :: 3.11
Classifier: Programming Language :: Python :: 3.12
Classifier: Operating System :: OS Independent
Classifier: Topic :: Documentation
Classifier: Topic :: Software Development :: Documentation
License-File: LICENSE
Requires-Dist: sphinx
Requires-Dist: pygments
Dynamic: license-file
